dodevops/__init__.py
dodevops/dodevops.py
dodevops-0.1.18.dist-info/entry_points.txt
dodevops-0.1.18.dist-info/METADATA
dodevops-0.1.18.dist-info/WHEEL
dodevops-0.1.18.dist-info/RECORD
