Metadata-Version: 2.1
Name: dodevops
Version: 0.1.18
Summary: Devops tool for deploying and managing resources on DigitalOcean
Home-page: https://github.com/Oakwright/dodevops
Keywords: devops,digitalocean,django
Author: Abby Oakwright
Author-email: abby.oakwright@gmail.com
Requires-Python: >=3.10,<4.0
Classifier: Programming Language :: Python :: 3
Classifier: Programming Language :: Python :: 3.10
Classifier: Programming Language :: Python :: 3.11
Requires-Dist: boto3 (>=1.31.57)
Requires-Dist: botocore (>=1.31.57)
Requires-Dist: configparser (>=6.0.0)
Requires-Dist: cryptography (>=41.0.4)
Requires-Dist: inquirer (>=3.1.3)
Requires-Dist: psycopg2-binary (>=2.9.8)
Requires-Dist: pydo (>=0.1.7)
Requires-Dist: python-dotenv (>=1.0.0)
Project-URL: Repository, https://github.com/Oakwright/dodevops
